fbi/__init__.py
fbi/__main__.py
fbi/cli.py
fileblocks-2023.5.30.dist-info/LICENSE
fileblocks-2023.5.30.dist-info/METADATA
fileblocks-2023.5.30.dist-info/WHEEL
fileblocks-2023.5.30.dist-info/entry_points.txt
fileblocks-2023.5.30.dist-info/top_level.txt
fileblocks-2023.5.30.dist-info/RECORD
