Metadata-Version: 2.1
Name: fileblocks
Version: 2023.5.30
Summary: Walk the line, Byte by Byte Analysis
Home-page: https://github.com/jblukach/fbi
Author: John Lukach
Author-email: hello@lukach.io
License: Apache-2.0
Requires-Python: >=3.7
License-File: LICENSE
Requires-Dist: blake3
Requires-Dist: pybloomfiltermmap3
Requires-Dist: requests
Requires-Dist: tqdm
